<?xml version="1.0" encoding="utf-8" ?>
<dwsync>
<file name="AdController.class.php" server="hyu2652530001.my3w.com//htdocs/" local="131354933612404595" remote="131343840000000000" Dst="0" />
<file name="IndexController.class.php" server="hyu2652530001.my3w.com//htdocs/" local="131354933613595442" remote="131343840000000000" Dst="0" />
<file name="LinkController.class.php" server="hyu2652530001.my3w.com//htdocs/" local="131354933614716234" remote="131343840000000000" Dst="0" />
<file name="BackupController.class.php" server="hyu2652530001.my3w.com//htdocs/" local="131354933616457473" remote="131343840000000000" Dst="0" />
<file name="MailerController.class.php" server="hyu2652530001.my3w.com//htdocs/" local="131354933617328087" remote="131343840000000000" Dst="0" />
<file name="MainController.class.php" server="hyu2652530001.my3w.com//htdocs/" local="131354933617788420" remote="131343840000000000" Dst="0" />
<file name="NavController.class.php" server="hyu2652530001.my3w.com//htdocs/" local="131354933622221565" remote="131343840000000000" Dst="0" />
<file name="MenuController.class.php" server="hyu2652530001.my3w.com//htdocs/" local="131354933622501758" remote="131343840000000000" Dst="0" />
<file name="NavcatController.class.php" server="hyu2652530001.my3w.com//htdocs/" local="131354933623432423" remote="131343840000000000" Dst="0" />
<file name="PluginController.class.php" server="hyu2652530001.my3w.com//htdocs/" local="131354933623902755" remote="131343840600000000" Dst="0" />
<file name="PublicController.class.php" server="hyu2652530001.my3w.com//htdocs/" local="131354933625894167" remote="131343840600000000" Dst="0" />
<file name="RbacController.class.php" server="hyu2652530001.my3w.com//htdocs/" local="131354933629156486" remote="131343840600000000" Dst="0" />
<file name="RouteController.class.php" server="hyu2652530001.my3w.com//htdocs/" local="131354933632118592" remote="131343840600000000" Dst="0" />
<file name="SettingController.class.php" server="hyu2652530001.my3w.com//htdocs/" local="131354933632328746" remote="131343840000000000" Dst="0" />
<file name="SlidecatController.class.php" server="hyu2652530001.my3w.com//htdocs/" local="131354933633369475" remote="131343840600000000" Dst="0" />
<file name="SlideController.class.php" server="hyu2652530001.my3w.com//htdocs/" local="131354933633419522" remote="131343840600000000" Dst="0" />
<file name="StorageController.class.php" server="hyu2652530001.my3w.com//htdocs/" local="131354933634440237" remote="131343840600000000" Dst="0" />
<file name="UserController.class.php" server="hyu2652530001.my3w.com//htdocs/" local="131354933634510285" remote="131343840600000000" Dst="0" />
<file name="VariableController.class.php" server="hyu2652530001.my3w.com//htdocs/" local="131354933635691127" remote="131343837600000000" Dst="0" />
</dwsync>