<?xml version="1.0" encoding="utf-8" ?>
<dwsync>
<file name="58d9f623c5567.png" server="hyu2652530001.my3w.com//htdocs/" local="131354935958125766" remote="131351241000000000" Dst="0" />
<file name="58d9f6669d08c.png" server="hyu2652530001.my3w.com//htdocs/" local="131354935962608951" remote="131351241600000000" Dst="0" />
<file name="58da2a6abd178.png" server="hyu2652530001.my3w.com//htdocs/" local="131354935967202216" remote="131351374800000000" Dst="0" />
<file name="58d9f6bb24242.png" server="hyu2652530001.my3w.com//htdocs/" local="131354935967207221" remote="131351242800000000" Dst="0" />
<file name="58da2aac39fc0.png" server="hyu2652530001.my3w.com//htdocs/" local="131354935971135003" remote="131351375400000000" Dst="0" />
<file name="58da2ad29977f.png" server="hyu2652530001.my3w.com//htdocs/" local="131354935971490255" remote="131351376000000000" Dst="0" />
<file name="58da3cf78e95f.png" server="hyu2652530001.my3w.com//htdocs/" local="131354935972836211" remote="131351422200000000" Dst="0" />
<file name="58da3d71d2918.png" server="hyu2652530001.my3w.com//htdocs/" local="131354935976093523" remote="131351423400000000" Dst="0" />
<file name="58da3df981774.png" server="hyu2652530001.my3w.com//htdocs/" local="131354935977559561" remote="131351425200000000" Dst="0" />
<file name="58da3dbd2acfc.png" server="hyu2652530001.my3w.com//htdocs/" local="131354935977834756" remote="131351424600000000" Dst="0" />
<file name="58da3e9488385.png" server="hyu2652530001.my3w.com//htdocs/" local="131354935982175627" remote="131351426400000000" Dst="0" />
<file name="58da3f3b7e1b2.png" server="hyu2652530001.my3w.com//htdocs/" local="131354935986018352" remote="131351428200000000" Dst="0" />
<file name="58da4078acf4a.png" server="hyu2652530001.my3w.com//htdocs/" local="131354936001633122" remote="131351431200000000" Dst="0" />
<file name="58da437ec165c.png" server="hyu2652530001.my3w.com//htdocs/" local="131354936007817516" remote="131351439000000000" Dst="0" />
<file name="58da43b99d576.png" server="hyu2652530001.my3w.com//htdocs/" local="131354936012413070" remote="131351439600000000" Dst="0" />
<file name="58da46545664f.png" server="hyu2652530001.my3w.com//htdocs/" local="131354936018115934" remote="131351446200000000" Dst="0" />
<file name="58da46cf8cc92.png" server="hyu2652530001.my3w.com//htdocs/" local="131354936022639273" remote="131351447400000000" Dst="0" />
<file name="58da47ed6ab8a.png" server="hyu2652530001.my3w.com//htdocs/" local="131354936028625250" remote="131351450400000000" Dst="0" />
<file name="58da48ea83563.png" server="hyu2652530001.my3w.com//htdocs/" local="131354936030946901" remote="131351452800000000" Dst="0" />
<file name="58da492cbfc45.png" server="hyu2652530001.my3w.com//htdocs/" local="131354936037871814" remote="131351453400000000" Dst="0" />
<file name="58da499f2812d.png" server="hyu2652530001.my3w.com//htdocs/" local="131354936039707448" remote="131351454600000000" Dst="0" />
<file name="58da4a3aba963.png" server="hyu2652530001.my3w.com//htdocs/" local="131354936046377348" remote="131351456400000000" Dst="0" />
<file name="58da4ae37101f.png" server="hyu2652530001.my3w.com//htdocs/" local="131354936048699002" remote="131351458200000000" Dst="0" />
<file name="58da4c7c342e7.png" server="hyu2652530001.my3w.com//htdocs/" local="131354936055774020" remote="131351461800000000" Dst="0" />
<file name="58da4f8ea3f47.png" server="hyu2652530001.my3w.com//htdocs/" local="131354936057695387" remote="131351470200000000" Dst="0" />
<file name="58da508073942.png" server="hyu2652530001.my3w.com//htdocs/" local="131354936065070615" remote="131351472600000000" Dst="0" />
<file name="58da508e35f1a.png" server="hyu2652530001.my3w.com//htdocs/" local="131354936065641027" remote="131351472600000000" Dst="0" />
<file name="58da5905b2b19.png" server="hyu2652530001.my3w.com//htdocs/" local="131354936073636705" remote="131351494200000000" Dst="0" />
<file name="58da58c23b3cc.png" server="hyu2652530001.my3w.com//htdocs/" local="131354936086405769" remote="131351493600000000" Dst="0" />
<file name="58da5a2380c7d.png" server="hyu2652530001.my3w.com//htdocs/" local="131354936088857505" remote="131351497200000000" Dst="0" />
<file name="58da5e9608935.png" server="hyu2652530001.my3w.com//htdocs/" local="131354936093821025" remote="131351508600000000" Dst="0" />
</dwsync>